MANIFEST.in
README.rst
setup.cfg
setup.py
wlfilebrowser/__init__.py
wlfilebrowser/base.py
wlfilebrowser/decorators.py
wlfilebrowser/fields.py
wlfilebrowser/forms.py
wlfilebrowser/functions.py
wlfilebrowser/models.py
wlfilebrowser/settings.py
wlfilebrowser/storage.py
wlfilebrowser/urls.py
wlfilebrowser/views.py
wlfilebrowser.egg-info/PKG-INFO
wlfilebrowser.egg-info/SOURCES.txt
wlfilebrowser.egg-info/dependency_links.txt
wlfilebrowser.egg-info/not-zip-safe
wlfilebrowser.egg-info/top_level.txt
wlfilebrowser/locale/zh_CN/LC_MESSAGES/django.mo
wlfilebrowser/locale/zh_CN/LC_MESSAGES/django.po
wlfilebrowser/locale/zh_TW/LC_MESSAGES/django.mo
wlfilebrowser/locale/zh_TW/LC_MESSAGES/django.po
wlfilebrowser/static/wlfilebrowser/css/rtl.css
wlfilebrowser/static/wlfilebrowser/css/wlfilebrowser.css
wlfilebrowser/static/wlfilebrowser/img/wlfilebrowser_icon_delete.gif
wlfilebrowser/static/wlfilebrowser/img/wlfilebrowser_icon_delete_hover.gif
wlfilebrowser/static/wlfilebrowser/img/wlfilebrowser_icon_rename.gif
wlfilebrowser/static/wlfilebrowser/img/wlfilebrowser_icon_rename_hover.gif
wlfilebrowser/static/wlfilebrowser/img/wlfilebrowser_icon_select.gif
wlfilebrowser/static/wlfilebrowser/img/wlfilebrowser_icon_select_disabled.gif
wlfilebrowser/static/wlfilebrowser/img/wlfilebrowser_icon_select_hover.gif
wlfilebrowser/static/wlfilebrowser/img/wlfilebrowser_icon_show.gif
wlfilebrowser/static/wlfilebrowser/img/wlfilebrowser_icon_show_hover.gif
wlfilebrowser/static/wlfilebrowser/img/wlfilebrowser_icon_showversions_hover.gif
wlfilebrowser/static/wlfilebrowser/img/wlfilebrowser_type_.gif
wlfilebrowser/static/wlfilebrowser/img/wlfilebrowser_type_audio.gif
wlfilebrowser/static/wlfilebrowser/img/wlfilebrowser_type_code.gif
wlfilebrowser/static/wlfilebrowser/img/wlfilebrowser_type_document.gif
wlfilebrowser/static/wlfilebrowser/img/wlfilebrowser_type_folder.gif
wlfilebrowser/static/wlfilebrowser/img/wlfilebrowser_type_image.gif
wlfilebrowser/static/wlfilebrowser/img/wlfilebrowser_type_video.gif
wlfilebrowser/static/wlfilebrowser/js/AddWlFileBrowser.js
wlfilebrowser/static/wlfilebrowser/js/FB_CKEditor.js
wlfilebrowser/static/wlfilebrowser/js/FB_FileBrowseField.js
