Metadata-Version: 1.0
Name: wlfilebrowser
Version: 1.9
Summary: a dependency for the WenlinCMS.
Home-page: http://wenlincms.com
Author: Feichi Long
Author-email: feichi@longfeichi.com
License: UNKNOWN
Platform: UNKNOWN
